sovant/__init__.py
sovant/base_client.py
sovant/client.py
sovant/exceptions.py
sovant/models.py
sovant/types.py
sovant/resources/__init__.py
sovant/resources/memories.py
sovant/resources/threads.py
sovant-1.3.0.dist-info/licenses/LICENSE
sovant-1.3.0.dist-info/METADATA
sovant-1.3.0.dist-info/WHEEL
sovant-1.3.0.dist-info/top_level.txt
sovant-1.3.0.dist-info/RECORD
