Metadata-Version: 2.4
Name: sovant
Version: 1.3.0
Summary: Sovant Memory-as-a-Service Python SDK
Author: Sovant
License: MIT
Project-URL: Documentation, https://sovant.ai/docs
Project-URL: Source, https://github.com/hechin91/sovant-ai
Project-URL: Tracker, https://github.com/hechin91/sovant-ai/issues
Requires-Python: >=3.10
License-File: LICENSE
Requires-Dist: httpx>=0.27.0
Requires-Dist: pydantic>=2.8.2
Dynamic: license-file
